gravitum/__init__.py
gravitum/endian.py
gravitum/exceptions.py
gravitum/integer.py
gravitum/utils.py
gravitum/virtual_pointer.py
gravitum/decompiler_builtins/__init__.py
gravitum/decompiler_builtins/ghidra.py
gravitum/decompiler_builtins/ida.py
gravitum-0.2.1.dist-info/LICENSE
gravitum-0.2.1.dist-info/METADATA
gravitum-0.2.1.dist-info/WHEEL
gravitum-0.2.1.dist-info/top_level.txt
gravitum-0.2.1.dist-info/RECORD
